LICENSE
MANIFEST.in
pyproject.toml
requirements.txt
setup.py
outliertree/__init__.py
outliertree/outlier_cpp_interface.pyx
outliertree.egg-info/PKG-INFO
outliertree.egg-info/SOURCES.txt
outliertree.egg-info/dependency_links.txt
outliertree.egg-info/top_level.txt
src/cat_outlier.cpp
src/clusters.cpp
src/fit_model.cpp
src/misc.cpp
src/outlier_tree.hpp
src/predict.cpp
src/split.cpp