Metadata-Version: 2.1
Name: outliertree
Version: 1.9.0
Summary: Explainable outlier detection through smart decision tree conditioning
Home-page: https://github.com/david-cortes/outliertree
Author: David Cortes
Keywords: outlier,anomaly,gritbot
License-File: LICENSE
